circus/__init__.py
circus/_version.py
circus/benchmarking.py
circus/clustering.py
circus/config.params
circus/converting.py
circus/deconverting.py
circus/extracting.py
circus/filtering.py
circus/fitting.py
circus/gathering.py
circus/merging.py
circus/thresholding.py
circus/whitening.py
circus/analyses/__init__.py
circus/analyses/display_amplitudes.py
circus/analyses/display_isi.py
circus/analyses/display_template.py
circus/analyses/display_templates.py
circus/analyses/inspect_consistency_clustering_fitting.py
circus/analyses/utils.py
circus/analyses/clustering/__init__.py
circus/analyses/clustering/inspect_clusters_projections.py
circus/analyses/clustering/inspect_clusters_snippets.py
circus/analyses/clustering/inspect_scalar_products.py
circus/analyses/clustering/inspect_template_similarities.py
circus/analyses/fitting/__init__.py
circus/analyses/fitting/inspect_amplitude_pdfs.py
circus/analyses/fitting/inspect_autocorrelograms.py
circus/analyses/fitting/inspect_fitted_snippets.py
circus/analyses/fitting/inspect_nbs_spikes.py
circus/analyses/fitting/inspect_rpvs.py
circus/analyses/merging/__init__.py
circus/analyses/merging/inspect_similarities_vs_support.py
circus/analyses/whitening/__init__.py
circus/analyses/whitening/inspect_basis_waveforms.py
circus/analyses/whitening/inspect_collected_waveforms.py
circus/analyses/whitening/inspect_spatial_matrix.py
circus/analyses/whitening/inspect_thresholds.py
circus/files/__init__.py
circus/files/arf.py
circus/files/blackrock.py
circus/files/brw.py
circus/files/datafile.py
circus/files/hdf5.py
circus/files/kwd.py
circus/files/maxwell.py
circus/files/mcd.py
circus/files/mcs_raw_binary.py
circus/files/mda.py
circus/files/neuralynx.py
circus/files/neurofile.py
circus/files/nix.py
circus/files/npy.py
circus/files/nwb.py
circus/files/openephys.py
circus/files/plexon.py
circus/files/raw_binary.py
circus/files/rhd.py
circus/files/utils/__init__.py
circus/files/utils/brpylib.py
circus/icons/gimp-tool-color-picker.png
spyking_circus-1.1.0.dist-info/AUTHORS
spyking_circus-1.1.0.dist-info/LICENSE
spyking_circus-1.1.0.dist-info/METADATA
spyking_circus-1.1.0.dist-info/WHEEL
spyking_circus-1.1.0.dist-info/entry_points.txt
spyking_circus-1.1.0.dist-info/top_level.txt
spyking_circus-1.1.0.dist-info/RECORD
