Metadata-Version: 2.1
Name: spyking-circus
Version: 1.1.0
Summary: Fast spike sorting by template matching
Home-page: http://spyking-circus.rtfd.org
Author: Pierre Yger and Olivier Marre
Author-email: pierre.yger@inserm.fr
License: License :: OSI Approved :: CeCILL-2.1
Keywords: spike sorting template matching tetrodes extracellular
Platform: UNKNOWN
Classifier: Development Status :: 4 - Beta
Classifier: Environment :: Console
Classifier: Intended Audience :: Science/Research
Classifier: License :: Other/Proprietary License
Classifier: Natural Language :: English
Classifier: Operating System :: OS Independent
Classifier: Programming Language :: Python :: 2
Classifier: Programming Language :: Python :: 3
Classifier: Topic :: Scientific/Engineering :: Bio-Informatics
License-File: LICENSE
License-File: AUTHORS
Requires-Dist: mpi4py
Requires-Dist: numpy
Requires-Dist: cython
Requires-Dist: scipy
Requires-Dist: matplotlib
Requires-Dist: h5py
Requires-Dist: colorama
Requires-Dist: psutil
Requires-Dist: tqdm
Requires-Dist: blosc
Requires-Dist: statsmodels
Requires-Dist: setuptools
Provides-Extra: beer
Requires-Dist: scikit-learn ; extra == 'beer'
